py_attack/__init__.py
py_attack/__main__.py
py_attack/attack.py
py_attack/domains.py
py_attack/filter.py
py_attack/types.py
py_attack/utils.py
py_attack-0.0.1.dist-info/LICENSE
py_attack-0.0.1.dist-info/METADATA
py_attack-0.0.1.dist-info/WHEEL
py_attack-0.0.1.dist-info/top_level.txt
py_attack-0.0.1.dist-info/RECORD
