Metadata-Version: 2.1
Name: py-attack
Version: 0.0.1
Summary: Python implementation and visualization of the ATT&CK framework
Home-page: https://github.com/Thijsvanede/py-attack
Author: Thijs van Ede
Author-email: t.s.vanede@utwente.nl
Classifier: Programming Language :: Python :: 3
Classifier: License :: OSI Approved :: MIT License
Classifier: Operating System :: OS Independent
License-File: LICENSE
